src/meta_prompt/__init__.py
src/meta_prompt/server.py
mseep_meta_prompt_mcp-0.1.2.dist-info/METADATA
mseep_meta_prompt_mcp-0.1.2.dist-info/WHEEL
mseep_meta_prompt_mcp-0.1.2.dist-info/entry_points.txt
mseep_meta_prompt_mcp-0.1.2.dist-info/licenses/LICENSE
mseep_meta_prompt_mcp-0.1.2.dist-info/RECORD
