Metadata-Version: 2.4
Name: mseep-meta-prompt-mcp
Version: 0.1.2
Summary: Add your description here
Author-email: mseep <support@skydeck.ai>
License-File: LICENSE
Requires-Python: >=3.13
Requires-Dist: fastmcp>=2.3.4
Requires-Dist: langchain-anthropic>=0.3.13
Requires-Dist: langchain-google-genai>=2.1.4
Requires-Dist: langchain-openai>=0.3.17
Requires-Dist: langchain>=0.3.25
Requires-Dist: langgraph>=0.4.5
Requires-Dist: mcp[cli]>=1.9.0
